multiprocplus/__init__.py
multiprocplus/async_caller.py
multiprocplus/multi_process.py
multiprocplus-0.2.dist-info/METADATA
multiprocplus-0.2.dist-info/WHEEL
multiprocplus-0.2.dist-info/license
multiprocplus-0.2.dist-info/top_level.txt
multiprocplus-0.2.dist-info/RECORD
