Metadata-Version: 2.1
Name: multiprocplus
Version: 0.2
Summary: a drop-in and easy-use enhancement for multiprcocessing
Home-page: https://github.com/yinglang/multiprocplus
Author: hui
Author-email: y19941010@126.com
License: BSD
Project-URL: Bug Tracker, https://github.com/yinglang/multiprocplus/issues
Project-URL: Source Code, https://github.com/yinglang/multiprocplus
Keywords: replace for loop by multi processing
Platform: unix
Platform: linux
Platform: osx
Platform: cygwin
Platform: win32
Classifier: Development Status :: 4 - Beta 
Classifier: Environment :: Console
Classifier: Intended Audience :: Developers
Classifier: License :: OSI Approved :: BSD License
Classifier: Operating System :: OS Independent
Classifier: Programming Language :: Python :: 3
Classifier: Programming Language :: Python :: 3.4
Classifier: Programming Language :: Python :: 3.5
Classifier: Programming Language :: Python :: 3.6
Classifier: Programming Language :: Python :: 3.7
Classifier: Programming Language :: Python :: 3.8
Classifier: Programming Language :: Python :: 3.9
Classifier: Topic :: Utilities
Classifier: Topic :: Software Development :: Libraries :: Python Modules
Requires-Python: >=3
